---

layout: java助记符

title: java助记符

tags: Web

categories: Web

top: 22

path: /article/1653658581

abbrlink: 1653658581

date: 2022-05-29 21:36:28


---

# 字节码组成

Java字节码是Java虚拟机（JVM）执行的指令集，它由编译器将Java源代码编译生成。Java字节码存储在.class文件中，.class文件的结构遵循严格的规范，称为“Class文件格式”。Class文件格式定义了字节码的各个部分及其布局。

以下是Java Class文件的结构：

### Class文件结构

1. **魔数（Magic Number）**：
    - Class文件的前4个字节是魔数，用于标识这是一个Class文件。魔数的值是`0xCAFEBABE`。
2. **版本号（Version Number）**：
    - 紧接魔数之后的是Class文件的版本号，包括次版本号（minor version）和主版本号（major version）。次版本号和主版本号各占2个字节。
3. **常量池（Constant Pool）**：
    - 常量池是一个表，包含了Class文件中使用的所有常量，如字符串、整数、浮点数、类和方法引用等。常量池的大小由一个2字节的数字指定，表示常量池中的项数。
4. **访问标志（Access Flags）**：
    - 2个字节的访问标志，表示类或接口的访问权限和属性，如public、final、abstract等。
5. **类索引、父类索引和接口索引集合**：
    - 类索引（2字节）：指向常量池中的一个项，表示这个类的全限定名。
    - 父类索引（2字节）：指向常量池中的一个项，表示这个类的父类的全限定名。对于`java.lang.Object`类，父类索引为0。
    - 接口索引集合：一个接口索引集合，表示这个类实现的所有接口。每个接口索引占2个字节。
6. **字段表（Fields）**：
    - 字段表包含了类中定义的所有字段。每个字段都有自己的描述符，包括字段的名称、类型、访问权限等。
7. **方法表（Methods）**：
    - 方法表包含了类中定义的所有方法。每个方法都有自己的描述符，包括方法的名称、返回类型、参数类型、访问权限等。
8. **属性表（Attributes）**：
    - 属性表包含了Class文件的附加信息，如源文件名、调试信息、注解等。属性表可以出现在Class文件的多个部分，包括类定义、字段和方法。

### Class文件结构图示

```plaintext
+---------------------+
| Magic Number        |  // 0xCAFEBABE
+---------------------+
| Version Number      |  // minor_version and major_version
+---------------------+
| Constant Pool Count |  // Number of entries in the constant pool
+---------------------+
| Constant Pool       |  // Constant pool entries
+---------------------+
| Access Flags        |  // Class access flags
+---------------------+
| This Class Index    |  // Index of this class in the constant pool
+---------------------+
| Super Class Index   |  // Index of the superclass in the constant pool
+---------------------+
| Interfaces Count    |  // Number of interfaces implemented by this class
+---------------------+
| Interfaces          |  // Interface indices
+---------------------+
| Fields Count        |  // Number of fields in this class
+---------------------+
| Fields              |  // Field entries
+---------------------+
| Methods Count       |  // Number of methods in this class
+---------------------+
| Methods             |  // Method entries
+---------------------+
| Attributes Count    |  // Number of attributes of this class
+---------------------+
| Attributes          |  // Attribute entries
+---------------------+
```

### 常量池（Constant Pool）

常量池是Class文件中最复杂的部分之一，它包含了不同类型的常量。常量池中的每个项都有一个标记（tag），表示常量的类型。常量池项的类型包括：

- `CONSTANT_Class`
- `CONSTANT_Fieldref`
- `CONSTANT_Methodref`
- `CONSTANT_InterfaceMethodref`
- `CONSTANT_String`
- `CONSTANT_Integer`
- `CONSTANT_Float`
- `CONSTANT_Long`
- `CONSTANT_Double`
- `CONSTANT_NameAndType`
- `CONSTANT_Utf8`
- `CONSTANT_MethodHandle`
- `CONSTANT_MethodType`
- `CONSTANT_InvokeDynamic`

每种类型的常量项都有不同的结构和内容。例如，`CONSTANT_Class`项包含一个指向常量池中`CONSTANT_Utf8`项的索引，用于表示类的全限定名。

### 字段表和方法表

字段表和方法表的结构类似，每个字段或方法都有以下信息：

- 访问标志（Access Flags）
- 名称索引（Name Index）
- 描述符索引（Descriptor Index）
- 属性计数（Attributes Count）
- 属性（Attributes）

字段和方法的属性可以包括注解、调试信息、方法体（对于方法）等。

### 属性表

属性表是一个灵活的结构，用于存储Class文件的附加信息。常见的属性包括：

- `Code`（方法的字节码）
- `LineNumberTable`（行号表，用于调试）
- `LocalVariableTable`（局部变量表，用于调试）
- `SourceFile`（源文件名）
- `Deprecated`（表示类、字段或方法已过时）
- `RuntimeVisibleAnnotations`（运行时可见的注解）

每个属性都有一个名称索引、长度和具体的属性数据。

### 总结

Java Class文件结构定义了Java字节码的布局和内容，通过这种结构，JVM可以加载、验证和执行Java字节码。了解Class文件结构对于字节码插桩、动态代理和自定义类加载器等高级编程技术非常有帮助。

JVM助记符（JVM Instructions or Bytecode
Mnemonics）是Java虚拟机执行的指令集的符号表示。这些助记符代表了JVM可以执行的各种操作，如加载、存储、算术运算、控制流等。在面试中，关于JVM助记符的题目可能会涉及以下几个方面：

### 常见面试题

1. **什么是JVM助记符？**

    - JVM助记符是Java字节码指令的符号表示，用于描述JVM执行的操作。每个助记符对应一个特定的字节码指令。

2. **解释以下助记符的含义和用途：`aload_0`、`istore_1`、`iadd`、`goto`。**

    - `aload_0`：从局部变量表加载对象引用（索引为0）。
    - `istore_1`：将整数值存储到局部变量表（索引为1）。
    - `iadd`：将两个整数值相加。
    - `goto`：无条件跳转到指定的字节码指令。

3. **JVM助记符是如何分类的？**

    - JVM助记符可以根据操作类型分类，如：
        - 加载和存储指令（Load and Store Instructions）
        - 算术和逻辑指令（Arithmetic and Logic Instructions）
        - 类型转换指令（Type Conversion Instructions）
        - 对象创建和操作指令（Object Creation and Manipulation Instructions）
        - 控制流指令（Control Flow Instructions）
        - 方法调用和返回指令（Method Invocation and Return Instructions）

4. **解释以下控制流助记符的用途：`ifeq`、`if_icmpne`、`tableswitch`、`lookupswitch`。**

    - `ifeq`：如果栈顶整数值等于0，则跳转到指定的字节码指令。
    - `if_icmpne`：如果栈顶两个整数值不相等，则跳转到指定的字节码指令。
    - `tableswitch`：根据栈顶整数值进行表驱动的跳转。
    - `lookupswitch`：根据栈顶整数值进行查找表驱动的跳转。

5. **什么是`invokestatic`指令，它与`invokevirtual`指令有何区别？**

    - `invokestatic`：调用静态方法，不需要对象实例。方法在编译时解析。
    - `invokevirtual`：调用实例方法，需要对象实例。方法在运行时通过对象的实际类型进行动态分派。

6. **解释以下助记符的用途：`new`、`newarray`、`anewarray`、`multianewarray`。**

    - `new`：创建一个新的对象实例。
    - `newarray`：创建一个新的基本类型数组。
    - `anewarray`：创建一个新的引用类型数组。
    - `multianewarray`：创建一个新的多维数组。

7. **什么是栈操作指令，举例说明其用途。**

    - 栈操作指令用于直接操作操作数栈，如

      ```
      push
      ```

      和

      ```
      pop
      ```

      操作。常见的栈操作指令包括：

        - `dup`：复制栈顶的值并将其压入栈顶。
        - `pop`：弹出栈顶的值。
        - `swap`：交换栈顶的两个值。
        - `dup2`：复制栈顶的两个值并将其压入栈顶。

8. **解释`ldc`和`ldc_w`指令的区别。**

    - `ldc`：从常量池中加载常量（索引为1字节）。
    - `ldc_w`：从常量池中加载常量（索引为2字节），用于常量池中的大索引。

9. **什么是类型转换指令，举例说明其用途。**

    - 类型转换指令用于将一种类型的值转换为另一种类型。常见的类型转换指令包括：
        - `i2f`：将整数值转换为浮点数值。
        - `f2i`：将浮点数值转换为整数值。
        - `i2d`：将整数值转换为双精度浮点数值。
        - `d2i`：将双精度浮点数值转换为整数值。

10. **解释`monitorenter`和`monitorexit`指令的用途。**

    - `monitorenter`：进入对象的监视器（用于同步块）。
    - `monitorexit`：退出对象的监视器（用于同步块）。

### 示例题目及解答

**题目1**：解释以下字节码指令的作用：

```plaintext
0: aload_0
1: getfield #2  // Field java/lang/String.value:Ljava/lang/String;
4: astore_1
5: return
```

**解答**：

- `aload_0`：从局部变量表加载对象引用（索引为0，即当前对象`this`）。
- `getfield`：获取对象的字段值（`java/lang/String.value`）。
- `astore_1`：将引用类型值存储到局部变量表（索引为1）。
- `return`：从方法返回。

**题目2**：解释以下字节码指令的作用：

```plaintext
0: iconst_5
1: istore_1
2: iload_1
3: iinc 1, 1
6: iload_1
7: iadd
8: istore_2
9: return
```

**解答**：

- `iconst_5`：将整数常量5压入栈顶。
- `istore_1`：将栈顶整数值存储到局部变量表（索引为1）。
- `iload_1`：从局部变量表加载整数值（索引为1）。
- `iinc 1, 1`：局部变量表中索引为1的整数值自增1。
- `iload_1`：从局部变量表加载整数值（索引为1）。
- `iadd`：将栈顶的两个整数值相加。
- `istore_2`：将相加结果存储到局部变量表（索引为2）。
- `return`：从方法返回。

这些题目和解答展示了JVM助记符的基本知识和常见用法，理解这些内容对于Java虚拟机的工作原理和性能优化非常有帮助。

在Java虚拟机（JVM）字节码中，`goto`是一个控制流助记符，用于实现无条件跳转。`goto`指令的主要用途是改变程序的执行顺序，使得控制流跳转到指定的字节码指令位置。

### `goto`指令的格式

`goto`指令的格式如下：

plaintext

Copy

```plaintext
goto <branchbyte1> <branchbyte2>
```

- `<branchbyte1>`和`<branchbyte2>`：这两个字节表示跳转的目标偏移量（以字节为单位）。偏移量是一个有符号的16位整数（short），表示从当前指令的下一条指令开始计算的跳转距离。

### `goto`指令的用途

`goto`指令可以用于以下几种情况：

1. **循环**：`goto`指令可以用于实现循环结构，例如`while`或`for`循环。
2. **条件跳转**：虽然条件跳转通常使用`if`指令，但在某些情况下可以使用`goto`指令配合条件判断实现更复杂的控制流。
3. **异常处理**：在异常处理代码中，`goto`指令可以用于跳转到异常处理块。
4. **代码优化**：编译器可以使用`goto`指令进行代码优化，减少不必要的指令执行。

### 示例代码

以下是一个使用`goto`指令实现简单循环的示例代码：

#### Java源代码

```java
public class GotoExample {
    public static void main(String[] args) {
        int i = 0;
        while (i < 5) {
            System.out.println(i);
            i++;
        }
    }
}
```

#### 对应的字节码

使用`javap -c GotoExample`命令查看编译后的字节码：

```plaintext
Compiled from "GotoExample.java"
public class GotoExample {
  public GotoExample();
    Code:
       0: aload_0
       1: invokespecial #1                  // Method java/lang/Object."<init>":()V
       4: return

  public static void main(java.lang.String[]);
    Code:
       0: iconst_0
       1: istore_1
       2: iload_1
       3: iconst_5
       4: if_icmpge     17
       7: getstatic     #2                  // Field java/lang/System.out:Ljava/io/PrintStream;
      10: iload_1
      11: invokevirtual #3                  // Method java/io/PrintStream.println:(I)V
      14: iinc          1, 1
      17: goto          2
      20: return
}
```

在这个字节码示例中，`goto`指令用于实现`while`循环：

- `0: iconst_0`：将常量0压入栈顶。
- `1: istore_1`：将栈顶的整数值存储到局部变量表（索引为1）。
- `2: iload_1`：从局部变量表加载整数值（索引为1）。
- `3: iconst_5`：将常量5压入栈顶。
- `4: if_icmpge 17`：如果栈顶两个整数值不小于，则跳转到字节码指令位置17。
- `7: getstatic #2`：获取`System.out`对象的引用。
- `10: iload_1`：从局部变量表加载整数值（索引为1）。
- `11: invokevirtual #3`：调用`println`方法，输出整数值。
- `14: iinc 1, 1`：局部变量表中索引为1的整数值自增1。
- `17: goto 2`：无条件跳转到字节码指令位置2，重新执行循环。
- `20: return`：从方法返回。

通过这个示例，可以看到`goto`指令在字节码中用于实现循环控制流，确保程序在满足条件时能够重复执行特定的代码块。